pdfcoordex/__init__.py
pdfcoordex/extractor.py
pdfcoordex-0.1.2.dist-info/METADATA
pdfcoordex-0.1.2.dist-info/WHEEL
pdfcoordex-0.1.2.dist-info/top_level.txt
pdfcoordex-0.1.2.dist-info/RECORD
